ts_fe/__init__.py
ts_fe/timeseries_processing/__init__.py
ts_fe/timeseries_processing/timeseries_processing.py
ts_fe-0.1.dist-info/LICENSE
ts_fe-0.1.dist-info/METADATA
ts_fe-0.1.dist-info/WHEEL
ts_fe-0.1.dist-info/top_level.txt
ts_fe-0.1.dist-info/RECORD
