Metadata-Version: 2.1
Name: ts-fe
Version: 0.1
Summary: timeseries processing to run any model
Home-page: https://github.com/EricSchles/ts_fe
Author: Eric Schles
Author-email: ericschles@gmail.com
License: MIT
Platform: UNKNOWN
Classifier: License :: OSI Approved :: MIT License
Classifier: Programming Language :: Python :: 3
Classifier: Programming Language :: Python :: 3.6
Classifier: Programming Language :: Python :: 3.7
Classifier: Programming Language :: Python :: 3.8
Classifier: Programming Language :: Python :: 3.9
License-File: LICENSE
Requires-Dist: pandas
Requires-Dist: numpy
